texto_no_espelho/__init__.py
texto_no_espelho/espelho.py
texto_no_espelho/texto_no_espelho/__init__.py
texto_no_espelho/texto_no_espelho/espelho.py
texto_no_espelho-0.0.2.dist-info/METADATA
texto_no_espelho-0.0.2.dist-info/WHEEL
texto_no_espelho-0.0.2.dist-info/top_level.txt
texto_no_espelho-0.0.2.dist-info/RECORD
