Metadata-Version: 2.1
Name: texto-no-espelho
Version: 0.0.2
Summary: Texto no espelho
Home-page: https://github.com/israelruiz2005/texto_no_espelho_package
Author: Israel Ruiz
Author-email: israelruiz2005@gmail.com
License: UNKNOWN
Platform: UNKNOWN
Requires-Python: >=3.8
